{
  "scenario_id": "scenario_28",
  "started_at": "2026-06-20T18:57:21.847Z",
  "status": "passed",
  "shots": [
    {
      "step": 1,
      "slug": "01_cockpit_header",
      "caption": "Course Cockpit: заголовок и pace mode",
      "narration": "Активный курс открывается в режиме v2-кабины.",
      "file": "01_cockpit_header.png",
      "taken_at": "2026-06-20T18:57:23.354Z",
      "viewport": {
        "width": 1400,
        "height": 900
      },
      "timings_ms": {
        "wait": 514,
        "streamlit_ready": 7,
        "screenshot": 294,
        "total": 815
      }
    },
    {
      "step": 2,
      "slug": "02_daily_briefing",
      "caption": "Daily briefing и активность",
      "narration": "Центральная колонка показывает обзор сессии и следующий блок.",
      "file": "02_daily_briefing.png",
      "taken_at": "2026-06-20T18:57:23.900Z",
      "viewport": {
        "width": 1400,
        "height": 900
      },
      "timings_ms": {
        "wait": 416,
        "streamlit_ready": 9,
        "screenshot": 75,
        "total": 500
      }
    },
    {
      "step": 3,
      "slug": "03_rotator_panel",
      "caption": "Rotator: карточки активностей курса",
      "narration": "Переключение между quiz, tutor и карточками без потери scope.",
      "file": "03_rotator_panel.png",
      "taken_at": "2026-06-20T18:57:24.395Z",
      "viewport": {
        "width": 1400,
        "height": 900
      },
      "timings_ms": {
        "wait": 414,
        "streamlit_ready": 8,
        "screenshot": 66,
        "total": 488
      }
    },
    {
      "step": 4,
      "slug": "04_graduation_progress",
      "caption": "Прогресс курса до graduation",
      "narration": "Видно, сколько осталось до завершения курса.",
      "file": "04_graduation_progress.png",
      "taken_at": "2026-06-20T18:57:24.932Z",
      "viewport": {
        "width": 1400,
        "height": 900
      },
      "timings_ms": {
        "wait": 409,
        "streamlit_ready": 9,
        "screenshot": 78,
        "total": 496
      }
    }
  ],
  "env": {
    "HOME_RAG_E2E_OFFLINE": "1",
    "E2E_API_PORT": "18000",
    "E2E_STREAMLIT_PORT": "18501"
  },
  "finished_at": "2026-06-20T18:57:24.932Z",
  "total_duration_ms": 3086,
  "shot_count": 4,
  "timings_summary": {
    "wait": {
      "sum": 1753,
      "avg": 438,
      "p95": 514
    },
    "streamlit_ready": {
      "sum": 33,
      "avg": 8,
      "p95": 9
    },
    "screenshot": {
      "sum": 513,
      "avg": 128,
      "p95": 294
    },
    "total": {
      "sum": 2299,
      "avg": 575,
      "p95": 815
    }
  }
}